rdp_algo/__init__.py
rdp_algo-0.1.1.dist-info/LICENSE
rdp_algo-0.1.1.dist-info/METADATA
rdp_algo-0.1.1.dist-info/WHEEL
rdp_algo-0.1.1.dist-info/top_level.txt
rdp_algo-0.1.1.dist-info/RECORD
